aicastle/__init__.py
aicastle/cli.py
aicastle/load_package_data.py
aicastle/chat/__init__.py
aicastle/chat/app.py
aicastle/chat/client.py
aicastle/chat/content_manager.py
aicastle/chat/filepaths.py
aicastle/chat/fine_tuning.py
aicastle/chat/function_call.py
aicastle/chat/hparams.py
aicastle/chat/tokens.py
aicastle/chat/utils.py
aicastle/deepracer/__init__.py
aicastle/deepracer/drfc/__init__.py
aicastle/deepracer/drfc/aws.py
aicastle/deepracer/vehicle/__init__.py
aicastle/deepracer/vehicle/api/__init__.py
aicastle/deepracer/vehicle/api/analyzer.py
aicastle/deepracer/vehicle/api/client.py
aicastle/deepracer/vehicle/api/constant.py
aicastle/deepracer/vehicle/api/controller.py
aicastle/deepracer/vehicle/api/ssh.py
aicastle/deepracer/vehicle/api/utils.py
aicastle/deepracer/vehicle/api/vehicle_control_module_content/__init__.py
aicastle/deepracer/vehicle/api/vehicle_control_module_content/custom.py
aicastle/deepracer/vehicle/api/vehicle_control_module_content/origin.py
aicastle/llm/__init__.py
aicastle/package_data/.aicastle/chat/.chatignore
aicastle/package_data/.aicastle/chat/.env.example
aicastle/package_data/.aicastle/chat/.finetuning
aicastle/package_data/.aicastle/chat/config.yml
aicastle/package_data/.aicastle/chat/system.txt
aicastle/package_data/.devcontainer/devcontainer.json
aicastle/utils/__init__.py
aicastle/utils/background.py
aicastle/utils/hash.py
aicastle/utils/json.py
aicastle/utils/load_data.py
aicastle/utils/path.py
aicastle-0.7.37.dist-info/METADATA
aicastle-0.7.37.dist-info/WHEEL
aicastle-0.7.37.dist-info/entry_points.txt
aicastle-0.7.37.dist-info/top_level.txt
aicastle-0.7.37.dist-info/RECORD
